pikkachu/__init__.py
pikkachu/cli.py
pikkachu/commands/__init__.py
pikkachu/commands/attack.py
pikkachu/commands/base.py
pikkachu/commands/hello.py
pikkachu/commands/news.py
pikkachu/commands/play.py
pikkachu-1.0.3.dist-info/DESCRIPTION.rst
pikkachu-1.0.3.dist-info/METADATA
pikkachu-1.0.3.dist-info/RECORD
pikkachu-1.0.3.dist-info/WHEEL
pikkachu-1.0.3.dist-info/entry_points.txt
pikkachu-1.0.3.dist-info/metadata.json
pikkachu-1.0.3.dist-info/top_level.txt
